MANIFEST.in
README.md
setup.py
nlutools/__init__.py
nlutools/cli.py
nlutools/config.py
nlutools/online_bert_client.py
nlutools/preprocess.py
nlutools/rpc_client.py
nlutools/sentence_split.py
nlutools/tools.py
nlutools/utils.py
nlutools.egg-info/PKG-INFO
nlutools.egg-info/SOURCES.txt
nlutools.egg-info/dependency_links.txt
nlutools.egg-info/entry_points.txt
nlutools.egg-info/not-zip-safe
nlutools.egg-info/requires.txt
nlutools.egg-info/top_level.txt
nlutools/config/bert_models.txt
nlutools/config/module_map_url.txt
nlutools/config/online_dev_hosts.txt
nlutools/config/stop_words.txt
nlutools/config/support_conf.txt
nlutools/config/version.txt
test/test.py