Metadata-Version: 2.1
Name: nlutools
Version: 2.1.4
Summary: nlu service tools
Home-page: https://www.ifchange.com
Author: ai3
Author-email: ai3@ifchange.com
License: Apache License 2.0
Platform: UNKNOWN
